{
  "cases": [
    {
      "alignment_relation": "offset",
      "bottom_h_W_m2K": 20.0,
      "coordinate_max_abs_error_m": 0.0,
      "group_id": "p1g_g000",
      "k_max_abs_error_W_mK": 0.0,
      "layout_kind": "clustered",
      "metric_abs_errors": {
        "bottom_heat_flux_W": 0.0,
        "energy_balance_relative_error": 0.0,
        "linear_residual": 0.0,
        "mean_deltaT_K": 0.0,
        "peak_deltaT_K": 0.0,
        "top_heat_flux_W": 0.0
      },
      "package_total_power_W": 4.0,
      "point_seed": 3652480404,
      "q_max_abs_error_W_m3": 0.0,
      "sample_id": "p1g_g000_t0_b0_p0",
      "solve_seconds": 1.5666903341189027,
      "source_count": 8,
      "split_role": "train",
      "temperature_max_abs_error_K": 0.0,
      "top_h_W_m2K": 1000.0
    },
    {
      "alignment_relation": "partly_aligned",
      "bottom_h_W_m2K": 120.0,
      "coordinate_max_abs_error_m": 0.0,
      "group_id": "p1g_g097",
      "k_max_abs_error_W_mK": 0.0,
      "layout_kind": "edge_balanced",
      "metric_abs_errors": {
        "bottom_heat_flux_W": 0.0,
        "energy_balance_relative_error": 0.0,
        "linear_residual": 0.0,
        "mean_deltaT_K": 0.0,
        "peak_deltaT_K": 0.0,
        "top_heat_flux_W": 0.0
      },
      "package_total_power_W": 6.0,
      "point_seed": 3855891658,
      "q_max_abs_error_W_m3": 0.0,
      "sample_id": "p1g_g097_t1_b1_p1",
      "solve_seconds": 1.5112470416352153,
      "source_count": 10,
      "split_role": "valid",
      "temperature_max_abs_error_K": 0.0,
      "top_h_W_m2K": 1400.0
    },
    {
      "alignment_relation": "partly_aligned",
      "bottom_h_W_m2K": 20.0,
      "coordinate_max_abs_error_m": 0.0,
      "group_id": "p1g_g112",
      "k_max_abs_error_W_mK": 0.0,
      "layout_kind": "mixed",
      "metric_abs_errors": {
        "bottom_heat_flux_W": 0.0,
        "energy_balance_relative_error": 0.0,
        "linear_residual": 0.0,
        "mean_deltaT_K": 0.0,
        "peak_deltaT_K": 0.0,
        "top_heat_flux_W": 0.0
      },
      "package_total_power_W": 4.0,
      "point_seed": 2149979339,
      "q_max_abs_error_W_m3": 0.0,
      "sample_id": "p1g_g112_t0_b0_p0",
      "solve_seconds": 1.4774036249145865,
      "source_count": 7,
      "split_role": "test",
      "temperature_max_abs_error_K": 0.0,
      "top_h_W_m2K": 1000.0
    },
    {
      "alignment_relation": "offset",
      "bottom_h_W_m2K": 20.0,
      "coordinate_max_abs_error_m": 0.0,
      "group_id": "p1g_g003",
      "k_max_abs_error_W_mK": 0.0,
      "layout_kind": "distributed",
      "metric_abs_errors": {
        "bottom_heat_flux_W": 0.0,
        "energy_balance_relative_error": 0.0,
        "linear_residual": 0.0,
        "mean_deltaT_K": 0.0,
        "peak_deltaT_K": 0.0,
        "top_heat_flux_W": 0.0
      },
      "package_total_power_W": 4.0,
      "point_seed": 187142465,
      "q_max_abs_error_W_m3": 0.0,
      "sample_id": "p1g_g003_t0_b0_p0",
      "solve_seconds": 1.5065704579465091,
      "source_count": 5,
      "split_role": "train",
      "temperature_max_abs_error_K": 0.0,
      "top_h_W_m2K": 1000.0
    },
    {
      "alignment_relation": "partly_aligned",
      "bottom_h_W_m2K": 20.0,
      "coordinate_max_abs_error_m": 0.0,
      "group_id": "p1g_g001",
      "k_max_abs_error_W_mK": 0.0,
      "layout_kind": "clustered",
      "metric_abs_errors": {
        "bottom_heat_flux_W": 0.0,
        "energy_balance_relative_error": 0.0,
        "linear_residual": 0.0,
        "mean_deltaT_K": 0.0,
        "peak_deltaT_K": 0.0,
        "top_heat_flux_W": 0.0
      },
      "package_total_power_W": 4.0,
      "point_seed": 942662102,
      "q_max_abs_error_W_m3": 0.0,
      "sample_id": "p1g_g001_t0_b0_p0",
      "solve_seconds": 1.5642594159580767,
      "source_count": 4,
      "split_role": "train",
      "temperature_max_abs_error_K": 0.0,
      "top_h_W_m2K": 1000.0
    },
    {
      "alignment_relation": "offset",
      "bottom_h_W_m2K": 20.0,
      "coordinate_max_abs_error_m": 0.0,
      "group_id": "p1g_g010",
      "k_max_abs_error_W_mK": 0.0,
      "layout_kind": "clustered",
      "metric_abs_errors": {
        "bottom_heat_flux_W": 0.0,
        "energy_balance_relative_error": 0.0,
        "linear_residual": 0.0,
        "mean_deltaT_K": 0.0,
        "peak_deltaT_K": 0.0,
        "top_heat_flux_W": 0.0
      },
      "package_total_power_W": 4.0,
      "point_seed": 1773381749,
      "q_max_abs_error_W_m3": 0.0,
      "sample_id": "p1g_g010_t0_b0_p0",
      "solve_seconds": 1.676978333387524,
      "source_count": 6,
      "split_role": "train",
      "temperature_max_abs_error_K": 0.0,
      "top_h_W_m2K": 1000.0
    },
    {
      "alignment_relation": "offset",
      "bottom_h_W_m2K": 20.0,
      "coordinate_max_abs_error_m": 0.0,
      "group_id": "p1g_g013",
      "k_max_abs_error_W_mK": 0.0,
      "layout_kind": "mixed",
      "metric_abs_errors": {
        "bottom_heat_flux_W": 0.0,
        "energy_balance_relative_error": 0.0,
        "linear_residual": 0.0,
        "mean_deltaT_K": 0.0,
        "peak_deltaT_K": 0.0,
        "top_heat_flux_W": 0.0
      },
      "package_total_power_W": 4.0,
      "point_seed": 1634427292,
      "q_max_abs_error_W_m3": 0.0,
      "sample_id": "p1g_g013_t0_b0_p0",
      "solve_seconds": 1.447608791757375,
      "source_count": 9,
      "split_role": "train",
      "temperature_max_abs_error_K": 0.0,
      "top_h_W_m2K": 1000.0
    },
    {
      "alignment_relation": "offset",
      "bottom_h_W_m2K": 20.0,
      "coordinate_max_abs_error_m": 0.0,
      "group_id": "p1g_g027",
      "k_max_abs_error_W_mK": 0.0,
      "layout_kind": "edge_balanced",
      "metric_abs_errors": {
        "bottom_heat_flux_W": 0.0,
        "energy_balance_relative_error": 0.0,
        "linear_residual": 0.0,
        "mean_deltaT_K": 0.0,
        "peak_deltaT_K": 0.0,
        "top_heat_flux_W": 0.0
      },
      "package_total_power_W": 4.0,
      "point_seed": 4144537182,
      "q_max_abs_error_W_m3": 0.0,
      "sample_id": "p1g_g027_t0_b0_p0",
      "solve_seconds": 1.5331882922910154,
      "source_count": 3,
      "split_role": "train",
      "temperature_max_abs_error_K": 0.0,
      "top_h_W_m2K": 1000.0
    }
  ],
  "checks": {
    "coordinates_m": true,
    "field_metric": true,
    "k_W_mK": true,
    "projected_temperature_K": true,
    "q_W_m3": true
  },
  "elapsed_seconds": 17.009330708999187,
  "factor_universe": [
    "alignment:offset",
    "alignment:partly_aligned",
    "bottom_h:120",
    "bottom_h:20",
    "layout:clustered",
    "layout:distributed",
    "layout:edge_balanced",
    "layout:mixed",
    "power:4",
    "power:6",
    "source_count:10",
    "source_count:3",
    "source_count:4",
    "source_count:5",
    "source_count:6",
    "source_count:7",
    "source_count:8",
    "source_count:9",
    "split:test",
    "split:train",
    "split:valid",
    "top_h:1000",
    "top_h:1400"
  ],
  "max_abs_error": {
    "coordinates_m": 0.0,
    "field_metric": 0.0,
    "k_W_mK": 0.0,
    "projected_temperature_K": 0.0,
    "q_W_m3": 0.0
  },
  "model_inference_runs": 0,
  "parent_config_sha256": "ab162724af61c745f82571e9c8f07102d5262c70a4817ace0900e894bfc4af83",
  "parent_dataset": "/Users/xuyihua/.codex/worktrees/5c97/3D IC Heat/data/heat3d_v6_p1g_geometry_deconfounded1024_v0",
  "parent_file_hash_failures": [],
  "parent_file_hashes_checked": 10240,
  "parent_manifest_sha256": "e5329d5cd6253510d87a4432d5f2ddae67259637810c29fdfb6ddf42621875a4",
  "representative_count": 8,
  "representative_selection": "deterministic_factor_set_cover_without_labels",
  "schema_version": "heat3d_v6_p1h_replay_audit_v1",
  "solver_node_count": 240825,
  "solver_shape": [
    65,
    65,
    57
  ],
  "status": "passed",
  "tolerances": {
    "coordinates_m": 0.0,
    "field_metric": 1e-10,
    "k_W_mK": 0.0,
    "projected_temperature_K": 1e-10,
    "q_W_m3": 0.0
  },
  "training_runs": 0
}
